ChangeLog
MANIFEST.in
README.rst
openstack-common.conf
setup.cfg
setup.py
tox.ini
melange/__init__.py
melange/client/__init__.py
melange/client/cli.py
melange/client/client.py
melange/client/exception.py
melange/client/inspector.py
melange/client/ipam_client.py
melange/client/template.py
melange/client/utils.py
melange/client/openstack/__init__.py
melange/client/openstack/common/__init__.py
melange/client/openstack/common/setup.py
melange/client/tests/__init__.py
melange/client/tests/functional/__init__.py
melange/client/tests/functional/factory.py
melange/client/tests/functional/template_test_helper.py
melange/client/tests/functional/test_cli.py
melange/client/tests/unit/__init__.py
melange/client/tests/unit/test_client.py
melange/client/tests/unit/test_inspector.py
melange/client/tests/unit/test_ipam_client.py
melange/client/tests/unit/test_utils.py
melange/client/tests/unit/helper/__init__.py
melange/client/tests/unit/helper/test_table.py
melange/client/views/__init__.py
melange/client/views/ip_route_list.tpl
melange/client/views/helpers/__init__.py
melange/client/views/helpers/table.py
python_melangeclient.egg-info/PKG-INFO
python_melangeclient.egg-info/SOURCES.txt
python_melangeclient.egg-info/dependency_links.txt
python_melangeclient.egg-info/entry_points.txt
python_melangeclient.egg-info/namespace_packages.txt
python_melangeclient.egg-info/not-zip-safe
python_melangeclient.egg-info/requires.txt
python_melangeclient.egg-info/top_level.txt
tools/pip-requires
tools/test-requires