Metadata-Version: 1.0
Name: python-melangeclient
Version: 0.2.2
Summary: Client library for OpenStack Melange API.
Home-page: https://github.com/openstack/python-melangeclient
Author: Openstack Melange Team
Author-email: openstack@lists.launchpad.net
License: Apache License, Version 2.0
Platform: UNKNOWN
Classifier: Development Status :: 5 - Production/Stable
Classifier: Environment :: Console
Classifier: Intended Audience :: Developers
Classifier: Intended Audience :: Information Technology
Classifier: License :: OSI Approved :: Apache Software License
Classifier: Operating System :: OS Independent
Classifier: Programming Language :: Python
